LICENSE
MANIFEST.in
README.md
pplugins.py
setup.cfg
setup.py
pplugins.egg-info/PKG-INFO
pplugins.egg-info/SOURCES.txt
pplugins.egg-info/dependency_links.txt
pplugins.egg-info/requires.txt
pplugins.egg-info/top_level.txt