Metadata-Version: 1.1
Name: pplugins
Version: 1.0.1
Summary: Process-based plugin framework
Home-page: https://github.com/JohnMaguire/pplugins
Author: John Maguire
Author-email: contact@johnmaguire.me
License: MIT
Download-URL: https://github.com/JohnMaguire/pplugins/tarball/1.0.1
Platform: UNKNOWN
Classifier: License :: OSI Approved :: MIT License
Classifier: Topic :: Software Development :: Libraries :: Application Frameworks
